pandera/__init__.py
pandera/_pandas_deprecated.py
pandera/_patch_numpy2.py
pandera/_version.py
pandera/config.py
pandera/constants.py
pandera/decorators.py
pandera/dtypes.py
pandera/errors.py
pandera/extensions.py
pandera/external_config.py
pandera/ibis.py
pandera/import_utils.py
pandera/inspection_utils.py
pandera/mypy.py
pandera/pandas.py
pandera/polars.py
pandera/py.typed
pandera/pyspark.py
pandera/system.py
pandera/utils.py
pandera/validation_depth.py
pandera/accessors/__init__.py
pandera/accessors/dask_accessor.py
pandera/accessors/modin_accessor.py
pandera/accessors/pandas_accessor.py
pandera/accessors/polars_accessor.py
pandera/accessors/pyspark_accessor.py
pandera/accessors/pyspark_sql_accessor.py
pandera/api/__init__.py
pandera/api/checks.py
pandera/api/extensions.py
pandera/api/function_dispatch.py
pandera/api/hypotheses.py
pandera/api/parsers.py
pandera/api/base/__init__.py
pandera/api/base/checks.py
pandera/api/base/error_handler.py
pandera/api/base/model.py
pandera/api/base/model_components.py
pandera/api/base/model_config.py
pandera/api/base/parsers.py
pandera/api/base/schema.py
pandera/api/base/types.py
pandera/api/dataframe/__init__.py
pandera/api/dataframe/components.py
pandera/api/dataframe/container.py
pandera/api/dataframe/model.py
pandera/api/dataframe/model_components.py
pandera/api/dataframe/model_config.py
pandera/api/ibis/__init__.py
pandera/api/ibis/components.py
pandera/api/ibis/container.py
pandera/api/ibis/model.py
pandera/api/ibis/types.py
pandera/api/pandas/__init__.py
pandera/api/pandas/array.py
pandera/api/pandas/components.py
pandera/api/pandas/container.py
pandera/api/pandas/model.py
pandera/api/pandas/model_config.py
pandera/api/pandas/types.py
pandera/api/polars/__init__.py
pandera/api/polars/components.py
pandera/api/polars/container.py
pandera/api/polars/model.py
pandera/api/polars/model_config.py
pandera/api/polars/types.py
pandera/api/polars/utils.py
pandera/api/pyspark/__init__.py
pandera/api/pyspark/column_schema.py
pandera-0.26.0.dist-info/licenses/LICENSE.txt
pandera-0.26.0.dist-info/METADATA
pandera-0.26.0.dist-info/WHEEL
pandera-0.26.0.dist-info/top_level.txt
pandera-0.26.0.dist-info/RECORD
