Metadata-Version: 2.4
Name: pandera
Version: 0.26.0
Summary: A light-weight and flexible data validation and testing tool for statistical data objects.
Author-email: Niels Bantilan <niels.bantilan@gmail.com>
License: MIT License
Project-URL: Documentation, https://pandera.readthedocs.io
Project-URL: Issue Tracker, https://github.com/pandera-dev/pandera/issues
Project-URL: Homepage, https://github.com/pandera-dev/pandera
Keywords: pandas,validation,data-structures
Classifier: Development Status :: 5 - Production/Stable
Classifier: Operating System :: OS Independent
Classifier: License :: OSI Approved :: MIT License
Classifier: Intended Audience :: Science/Research
Classifier: Programming Language :: Python
Classifier: Programming Language :: Python :: 3
Classifier: Programming Language :: Python :: 3.9
Classifier: Programming Language :: Python :: 3.10
Classifier: Programming Language :: Python :: 3.11
Classifier: Programming Language :: Python :: 3.12
Classifier: Programming Language :: Python :: 3.13
Classifier: Topic :: Scientific/Engineering
Requires-Python: >=3.9
License-File: LICENSE.txt
Requires-Dist: packaging>=20.0
Requires-Dist: pydantic
Requires-Dist: typeguard
Requires-Dist: typing_extensions
Requires-Dist: typing_inspect>=0.6.0
Provides-Extra: pandas
Requires-Dist: numpy>=1.24.4; extra == "pandas"
Requires-Dist: pandas>=2.1.1; extra == "pandas"
Provides-Extra: strategies
Requires-Dist: hypothesis>=6.92.7; extra == "strategies"
Provides-Extra: hypotheses
Requires-Dist: scipy; extra == "hypotheses"
Provides-Extra: io
Requires-Dist: pyyaml>=5.1; extra == "io"
Requires-Dist: black; extra == "io"
Requires-Dist: frictionless<=4.40.8; extra == "io"
Provides-Extra: mypy
Requires-Dist: pandas-stubs; extra == "mypy"
Provides-Extra: fastapi
Requires-Dist: fastapi; extra == "fastapi"
Provides-Extra: geopandas
Requires-Dist: geopandas<1.1.0; extra == "geopandas"
Requires-Dist: shapely; extra == "geopandas"
Provides-Extra: pyspark
Requires-Dist: pyspark[connect]<4.0.0,>=3.2.0; extra == "pyspark"
Provides-Extra: modin
Requires-Dist: modin; extra == "modin"
Requires-Dist: ray; extra == "modin"
Requires-Dist: dask[dataframe]; extra == "modin"
Requires-Dist: distributed; extra == "modin"
Provides-Extra: modin-ray
Requires-Dist: modin; extra == "modin-ray"
Requires-Dist: ray; extra == "modin-ray"
Provides-Extra: modin-dask
Requires-Dist: modin; extra == "modin-dask"
Requires-Dist: dask[dataframe]; extra == "modin-dask"
Requires-Dist: distributed; extra == "modin-dask"
Provides-Extra: dask
Requires-Dist: dask[dataframe]; extra == "dask"
Requires-Dist: distributed; extra == "dask"
Provides-Extra: ibis
Requires-Dist: ibis-framework>=9.0.0; extra == "ibis"
Provides-Extra: polars
Requires-Dist: polars>=0.20.0; extra == "polars"
Provides-Extra: all
Requires-Dist: hypothesis>=6.92.7; extra == "all"
Requires-Dist: scipy; extra == "all"
Requires-Dist: pyyaml>=5.1; extra == "all"
Requires-Dist: black; extra == "all"
Requires-Dist: frictionless<=4.40.8; extra == "all"
Requires-Dist: pyspark[connect]<4.0.0,>=3.2.0; extra == "all"
Requires-Dist: modin; extra == "all"
Requires-Dist: ray; extra == "all"
Requires-Dist: dask[dataframe]; extra == "all"
Requires-Dist: distributed; extra == "all"
Requires-Dist: pandas-stubs; extra == "all"
Requires-Dist: fastapi; extra == "all"
Requires-Dist: geopandas<1.1.0; extra == "all"
Requires-Dist: shapely; extra == "all"
Requires-Dist: ibis-framework>=9.0.0; extra == "all"
Requires-Dist: polars>=0.20.0; extra == "all"
Dynamic: license-file
